[{"title":"Nest.js 应用框架：分类","alias":"Nest.js：Category","url":"https://ninghao.net/course/7478"},{"title":"Nest.js 应用框架：内容关系","alias":"Nest.js：Relationships","url":"https://ninghao.net/course/7462"},{"title":"Nest.js 应用框架：身份验证","alias":"Nest.js：Authentication","url":"https://ninghao.net/course/7445"},{"title":"Nest.js 应用框架：用户","alias":"Nest.js：User","url":"https://ninghao.net/course/7430"},{"title":"Nest.js 应用框架：处理数据","alias":"Nest.js：Data Manipulation","url":"https://ninghao.net/course/7419"},{"title":"Nest.js 应用框架：数据库","alias":"Nest.js：Database","url":"https://ninghao.net/course/7405"},{"title":"Nest.js 应用框架：核心部件（3）","alias":"Nest.js：Core（3）","url":"https://ninghao.net/course/7386"},{"title":"Nest.js 应用框架：核心部件（2）","alias":"Nest.js：Core（2）","url":"https://ninghao.net/course/7365"},{"title":"Nest.js 应用框架：核心部件（1）","alias":"Nest.js：Core（1）","url":"https://ninghao.net/course/7341"},{"title":"电商网站案例：支付宝网页支付","alias":"W-Store：Alipay","url":"https://ninghao.net/course/7327"},{"title":"Nest.js 应用框架：请求与响应","alias":"Nest.js：Request and Response","url":"https://ninghao.net/course/7308"},{"title":"电商网站案例：调试与处理支付","alias":"WeApp Case：Debug","url":"https://ninghao.net/course/7286"},{"title":"电商网站案例：自定义支付方法","alias":"W-Store：Custom Payment","url":"https://ninghao.net/course/7269"},{"title":"电商小程序案例：绑定微信","alias":"WeApp Case：Bind WeChat","url":"https://ninghao.net/course/7256"},{"title":"电商小程序案例：微信登录","alias":"WeApp Case：WxLogin","url":"https://ninghao.net/course/7241"},{"title":"电商小程序案例：注册与登录","alias":"WeApp Case：User Login","url":"https://ninghao.net/course/7226"},{"title":"电商小程序案例：用户接口","alias":"WeApp Case：User API","url":"https://ninghao.net/course/7210"},{"title":"电商小程序案例：购物车编辑","alias":"WeApp Case：Cart Page Editing","url":"https://ninghao.net/course/7195"},{"title":"电商小程序案例：购物车页面","alias":"WeApp Case：Cart Page","url":"https://ninghao.net/course/7184"},{"title":"电商小程序案例：购物车接口","alias":"WeApp Case：Cart API","url":"https://ninghao.net/course/7168"},{"title":"电商小程序案例：购物面板","alias":"WeApp Case：Product Action Sheet","url":"https://ninghao.net/course/7150"},{"title":"电商小程序案例：购物工具栏","alias":"WeApp Case：Shopping TabBar","url":"https://ninghao.net/course/7136"},{"title":"电商小程序案例：产品视图","alias":"WeApp Case：Product View","url":"https://ninghao.net/course/7123"},{"title":"电商小程序案例：产品内容","alias":"WeApp Case：Product","url":"https://ninghao.net/course/7106"},{"title":"电商网站案例：主题","alias":"W-Store：Theme","url":"https://ninghao.net/course/7090"},{"title":"电商小程序案例：搜索","alias":"WeApp Case：Search","url":"https://ninghao.net/course/7071"},{"title":"电商网站案例：商店设置","alias":"W-Store：Settings","url":"https://ninghao.net/course/7058"},{"title":"电商小程序案例：内容分页","alias":"WeApp Case：Pagination","url":"https://ninghao.net/course/7041"},{"title":"Next.js：前端应用框架","alias":"Next.js：The React Framework","url":"https://ninghao.net/course/7024"},{"title":"电商网站案例：产品","alias":"W-Store：Product","url":"https://ninghao.net/course/7008"},{"title":"电商小程序案例：产品列表","alias":"WeApp Case：Product List","url":"https://ninghao.net/course/6986"},{"title":"电商网站案例：运行","alias":"W-Store：Dev Env","url":"https://ninghao.net/course/6971"},{"title":"电商小程序案例：页面结构","alias":"WeApp Case：Page","url":"https://ninghao.net/course/6952"},{"title":"商业网站案例：作品展示","alias":"Website Case：Portfolio","url":"https://ninghao.net/course/6931"},{"title":"商业网站案例：页面","alias":"Website Case：Page","url":"https://ninghao.net/course/6914"},{"title":"电商小程序案例：准备","alias":"WeApp Case：Prepare","url":"https://ninghao.net/course/6897"},{"title":"Electron 桌面应用：窗口","alias":"Electron：Window","url":"https://ninghao.net/course/6883"},{"title":"Electron 桌面应用：起步","alias":"Electron：Getting Started","url":"https://ninghao.net/course/6872"},{"title":"商业网站案例：在容器中运行","alias":"Website Case：Docker","url":"https://ninghao.net/course/6855"},{"title":"Nuxt.js：数据管理","alias":"Nuxt.js：Vuex","url":"https://ninghao.net/course/6842"},{"title":"Taro 框架：创建微信小程序","alias":"Taro","url":"https://ninghao.net/course/6821"},{"title":"Nuxt.js：异步数据","alias":"Nuxt.js：Async Data","url":"https://ninghao.net/course/6810"},{"title":"Nuxt.js：路由与视图","alias":"Nuxt.js","url":"https://ninghao.net/course/6797"},{"title":"TypeScript","alias":"TypeScript：JavaScript That Scales","url":"https://ninghao.net/course/6298"},{"title":"Flutter\b 移动应用：测试","alias":"Flutter：Testing","url":"https://ninghao.net/course/6769","pathHtml":"./src/ninghao/html/Testing.html","pathVideo":"./src/ninghao/video/Testing","children":[{"url":"https://ninghao.net/video/6771","title":"介绍","videoUrl":"https://ninghao.net/system/dynamics/video/flutter-test-00-00-intro-2071696491.mp4"},{"url":"https://ninghao.net/video/6772","title":"准备项目","videoUrl":"https://ninghao.net/system/dynamics/video/flutter-test-00-01-prepare-988248628.mp4"},{"url":"https://ninghao.net/video/6773","title":"创建 TestDemo","videoUrl":"https://ninghao.net/system/dynamics/video/flutter-test-00-02-test-demo-276585354.mp4"},{"url":"https://ninghao.net/video/6775","title":"Unit testing：单元测试","videoUrl":"https://ninghao.net/system/dynamics/video/flutter-test-01-01-unit-testing-1739612375.mp4"},{"url":"https://ninghao.net/video/6776","title":"运行测试","videoUrl":"https://ninghao.net/system/dynamics/video/flutter-test-01-02-run-test-75296062.mp4"},{"url":"https://ninghao.net/video/6778","title":"Widget Testing：测试小部件","videoUrl":"https://ninghao.net/system/dynamics/video/flutter-test-02-01-widget-test-531302239.mp4"},{"url":"https://ninghao.net/video/6779","title":"找到并验证小部件（Finder 与 Matcher 的用法）","videoUrl":"https://ninghao.net/system/dynamics/video/flutter-test-02-02-finder-matcher-1045706112.mp4"},{"url":"https://ninghao.net/video/6780","title":"测试小部件的点按行为","videoUrl":"https://ninghao.net/system/dynamics/video/flutter-test-02-03-test-widget-tap-1543613614.mp4"},{"url":"https://ninghao.net/video/6782","title":"Integration testing：集成测试","videoUrl":"https://ninghao.net/system/dynamics/video/flutter-test-03-01-integration-test-1044787979.mp4"},{"url":"https://ninghao.net/video/6783","title":"编写与运行集成测试","videoUrl":"https://ninghao.net/system/dynamics/video/flutter-test-03-02-write-run-integration-test-1180995330.mp4"}]},{"title":"Flutter\b 移动应用：国际化","alias":"Flutter：I18n","url":"https://ninghao.net/course/6748","pathHtml":"./src/ninghao/html/I18n.html","pathVideo":"./src/ninghao/video/I18n","children":[{"url":"https://ninghao.net/video/6750","title":"介绍","videoUrl":"https://ninghao.net/system/dynamics/video/flutter-i18n-00-00-intro-1497931328.mp4"},{"url":"https://ninghao.net/video/6751","title":"准备项目","videoUrl":"https://ninghao.net/system/dynamics/video/flutter-i18n-00-01-prepare-571627137.mp4"},{"url":"https://ninghao.net/video/6752","title":"创建 I18Demo 小部件","videoUrl":"https://ninghao.net/system/dynamics/video/flutter-i18n-00-02-i18n-demo-2127381064.mp4"},{"url":"https://ninghao.net/video/6754","title":"安装与配置 Flutter 应用的国际化","videoUrl":"https://ninghao.net/system/dynamics/video/flutter-i18n-01-01-flutter-localizations-1634100005.mp4"},{"url":"https://ninghao.net/video/6755","title":"配置 iOS 项目使用多种语言","videoUrl":"https://ninghao.net/system/dynamics/video/flutter-i18n-01-02-ios-localizations-230823385.mp4"},{"url":"https://ninghao.net/video/6756","title":"演示 Material 组件的多语言","videoUrl":"https://ninghao.net/system/dynamics/video/flutter-i18n-01-03-demo-material-localizations-373484708.mp4"},{"url":"https://ninghao.net/video/6757","title":"寻找 Localizations 小部件","videoUrl":"https://ninghao.net/system/dynamics/video/flutter-i18n-01-04-localizations-lookup-1260538826.mp4"},{"url":"https://ninghao.net/video/6758","title":"获取与设置语言和地区（理解 Locale 类与 Localizations 小部件）","videoUrl":"https://ninghao.net/system/dynamics/video/flutter-i18n-01-05-locale-localizations-1347211798.mp4"},{"url":"https://ninghao.net/video/6760","title":"定义本地化资源类","videoUrl":"https://ninghao.net/system/dynamics/video/flutter-i18n-02-01-custom-localizations-496537438.mp4"},{"url":"https://ninghao.net/video/6761","title":"加载本地化资源","videoUrl":"https://ninghao.net/system/dynamics/video/flutter-i18n-02-02-load-158778607.mp4"},{"url":"https://ninghao.net/video/6762","title":"使用本地化资源","videoUrl":"https://ninghao.net/system/dynamics/video/flutter-i18n-02-03-using-localizations-422386486.mp4"},{"url":"https://ninghao.net/video/6764","title":"Intl：定义需要翻译的信息","videoUrl":"https://ninghao.net/system/dynamics/video/flutter-i18n-03-01-intl-message-846605005.mp4"},{"url":"https://ninghao.net/video/6765","title":"提取信息模板并翻译信息","videoUrl":"https://ninghao.net/system/dynamics/video/flutter-i18n-03-02-extract-to-arb-459665547.mp4"},{"url":"https://ninghao.net/video/6766","title":"基于arb 生成 dart 文件","videoUrl":"https://ninghao.net/system/dynamics/video/flutter-i18n-03-03-generate-from-arb-162207476.mp4"},{"url":"https://ninghao.net/video/6767","title":"加载与使用本地化信息","videoUrl":"https://ninghao.net/system/dynamics/video/flutter-i18n-03-04-load-intl-2130320026.mp4"}]},{"title":"Flutter\b 移动应用：动画","alias":"Flutter：Animation","url":"https://ninghao.net/course/6736","pathHtml":"./src/ninghao/html/Animation.html","pathVideo":"./src/ninghao/video/Animation","children":[{"url":"https://ninghao.net/video/6738","title":"介绍","videoUrl":"https://ninghao.net/system/dynamics/video/flutter-animation-00-00-intro-1940143128.mp4"},{"url":"https://ninghao.net/video/6739","title":"准备项目","videoUrl":"https://ninghao.net/system/dynamics/video/flutter-animation-00-01-prepare-1339048063.mp4"},{"url":"https://ninghao.net/video/6740","title":"创建 AnimationDemo 小部件","videoUrl":"https://ninghao.net/system/dynamics/video/flutter-animation-00-02-animation-demo-18118197.mp4"},{"url":"https://ninghao.net/video/6742","title":"AnimationController：动画控制器","videoUrl":"https://ninghao.net/system/dynamics/video/flutter-animation-01-01-animation-controller-41931917.mp4"},{"url":"https://ninghao.net/video/6743","title":"使用动画的值","videoUrl":"https://ninghao.net/system/dynamics/video/flutter-animation-01-02-animation-value-1518711117.mp4"},{"url":"https://ninghao.net/video/6744","title":"动画的状态与运行","videoUrl":"https://ninghao.net/system/dynamics/video/flutter-animation-01-03-animation-status-993427091.mp4"},{"url":"https://ninghao.net/video/6745","title":"Tween：设置动画范围值（数字、颜色）","videoUrl":"https://ninghao.net/system/dynamics/video/flutter-animation-01-04-tween-1105836170.mp4"},{"url":"https://ninghao.net/video/6746","title":"Curve：动画曲线","videoUrl":"https://ninghao.net/system/dynamics/video/flutter-animation-01-05-curve-467532543.mp4"},{"url":"https://ninghao.net/video/6747","title":"AnimatedWidget：动画值有变化就自动重建自己的小部件","videoUrl":"https://ninghao.net/system/dynamics/video/flutter-animation-01-06-animated-widget-1600091023.mp4"}]},{"title":"Flutter\b 移动应用：网络请求","alias":"Flutter：HTTP","url":"https://ninghao.net/course/6720","pathHtml":"./src/ninghao/html/HTTP.html","pathVideo":"./src/ninghao/video/HTTP","children":[{"url":"https://ninghao.net/video/6722","title":"介绍","videoUrl":"https://ninghao.net/system/dynamics/video/flutter-http-00-00-intro-2098467951.mp4"},{"url":"https://ninghao.net/video/6723","title":"准备项目","videoUrl":"https://ninghao.net/system/dynamics/video/flutter-http-00-01-prepare-177279853.mp4"},{"url":"https://ninghao.net/video/6724","title":"创建 HttpDemo","videoUrl":"https://ninghao.net/system/dynamics/video/flutter-http-00-02-httpdemo-1458308856.mp4"},{"url":"https://ninghao.net/video/6726","title":"安装 http 包（升级 Flutter SDK）","videoUrl":"https://ninghao.net/system/dynamics/video/flutter-http-01-01-http-package-1208666454.mp4"},{"url":"https://ninghao.net/video/6734","title":"使用 http 客户端请求数据","videoUrl":"https://ninghao.net/system/dynamics/video/flutter-http-01-02-http-get-1403931416.mp4"},{"url":"https://ninghao.net/video/6728","title":"JSON 转换（dart:convert）","videoUrl":"https://ninghao.net/system/dynamics/video/flutter-http-01-03-convert-1921986880.mp4"},{"url":"https://ninghao.net/video/6729","title":"使用 Model 类转换数据：fromJson","videoUrl":"https://ninghao.net/system/dynamics/video/flutter-http-01-04-model-class-900034128.mp4"},{"url":"https://ninghao.net/video/6730","title":"使用 Model 类转换数据：toJson","videoUrl":"https://ninghao.net/system/dynamics/video/flutter-http-01-05-model-class-tojson-367468516.mp4"},{"url":"https://ninghao.net/video/6732","title":"使用请求数据：把响应的数据转换成自定义 Dart 对象","videoUrl":"https://ninghao.net/system/dynamics/video/flutter-http-03-01-using-response-data-139493692.mp4"},{"url":"https://ninghao.net/video/6733","title":"FutureBuilder：使用 Future 构建小部件","videoUrl":"https://ninghao.net/system/dynamics/video/flutter-http-03-02-futurebuilder-1775286065.mp4"}]},{"title":"Flutter\b 移动应用：输入","alias":"Flutter：MDC Input","url":"https://ninghao.net/course/6696","pathHtml":"./src/ninghao/html/MDC Input.html","pathVideo":"./src/ninghao/video/MDC Input","children":[{"url":"https://ninghao.net/video/6698","title":"介绍","videoUrl":"https://ninghao.net/system/dynamics/video/flutter-mdc-04-00-intro-1696327203.mp4"},{"url":"https://ninghao.net/video/6699","title":"整理：在演示列表里添加 FormDemo","videoUrl":"https://ninghao.net/system/dynamics/video/flutter-mdc-04-01-form-demo-30127410.mp4"},{"url":"https://ninghao.net/video/6700","title":"创建用户输入相关的小部件的演示页面","videoUrl":"https://ninghao.net/system/dynamics/video/flutter-mdc-04-02-input-demo-65765662.mp4"},{"url":"https://ninghao.net/video/6702","title":"Checkbox：复选框","videoUrl":"https://ninghao.net/system/dynamics/video/flutter-mdc-05-01-checkbox-2038103526.mp4"},{"url":"https://ninghao.net/video/6703","title":"CheckboxListTile：带标签与图标的复选框","videoUrl":"https://ninghao.net/system/dynamics/video/flutter-mdc-05-02-checkbox-listtile-1625303626.mp4"},{"url":"https://ninghao.net/video/6705","title":"Radio：单选按钮","videoUrl":"https://ninghao.net/system/dynamics/video/flutter-mdc-06-01-radio-1480961779.mp4"},{"url":"https://ninghao.net/video/6706","title":"RadioListTile：带标签与图标的单选按钮","videoUrl":"https://ninghao.net/system/dynamics/video/flutter-mdc-06-02-radio-listtile-277877697.mp4"},{"url":"https://ninghao.net/video/6708","title":"Switch：开关","videoUrl":"https://ninghao.net/system/dynamics/video/flutter-mdc-07-01-switch-1960266843.mp4"},{"url":"https://ninghao.net/video/6709","title":"SwitchListTile：带标签与图标的开关","videoUrl":"https://ninghao.net/system/dynamics/video/flutter-mdc-07-02-switch-list-tile-1073010775.mp4"},{"url":"https://ninghao.net/video/6711","title":"Slider：滑动选择器","videoUrl":"https://ninghao.net/system/dynamics/video/flutter-mdc-08-01-slider-267230010.mp4"},{"url":"https://ninghao.net/video/6713","title":"安装第三方包（演示安装 Intl 包）","videoUrl":"https://ninghao.net/system/dynamics/video/flutter-mdc-09-01-install-packages-1943030371.mp4"},{"url":"https://ninghao.net/video/6714","title":"显示格式化日期","videoUrl":"https://ninghao.net/system/dynamics/video/flutter-mdc-09-02-datetime-format-289118112.mp4"},{"url":"https://ninghao.net/video/6715","title":"showDatePicker：选择日期","videoUrl":"https://ninghao.net/system/dynamics/video/flutter-mdc-09-03-show-date-picker-221465446.mp4"},{"url":"https://ninghao.net/video/6716","title":"showDatePicker：获取选择的日期（async）","videoUrl":"https://ninghao.net/system/dynamics/video/flutter-mdc-09-04-get-selected-date-async-1450152190.mp4"},{"url":"https://ninghao.net/video/6717","title":"showTimePicker：时间选择器","videoUrl":"https://ninghao.net/system/dynamics/video/flutter-mdc-09-05-show-time-picker-295204855.mp4"},{"url":"https://ninghao.net/video/6718","title":"Future：异步程序","videoUrl":"https://ninghao.net/system/dynamics/video/flutter-mdc-09-06-future-1108634921.mp4"}]},{"title":"Flutter\b 移动应用：BLoC","alias":"Flutter：BLoC","url":"https://ninghao.net/course/6684","pathHtml":"./src/ninghao/html/BLoC.html","pathVideo":"./src/ninghao/video/BLoC","children":[{"url":"https://ninghao.net/video/6686","title":"介绍","videoUrl":"https://ninghao.net/system/dynamics/video/flutter-bloc-00-00-intro-138980165.mp4"},{"url":"https://ninghao.net/video/6687","title":"准备项目","videoUrl":"https://ninghao.net/system/dynamics/video/flutter-bloc-00-01-prepare-354454569.mp4"},{"url":"https://ninghao.net/video/6688","title":"创建 BlocDemo","videoUrl":"https://ninghao.net/system/dynamics/video/flutter-bloc-00-02-bloc-demo-1249726172.mp4"},{"url":"https://ninghao.net/video/6690","title":"BLoC：Business Logic Component","videoUrl":"https://ninghao.net/system/dynamics/video/flutter-bloc-01-01-intro-443502347.mp4"},{"url":"https://ninghao.net/video/6691","title":"BLoC 应用案例（记数器）：准备基本小部件","videoUrl":"https://ninghao.net/system/dynamics/video/flutter-bloc-01-02-bloc-counter-widget-693474019.mp4"},{"url":"https://ninghao.net/video/6692","title":"使用 InheritedWidget 传递 BLoC","videoUrl":"https://ninghao.net/system/dynamics/video/flutter-bloc-01-03-inherited-widget-186034471.mp4"},{"url":"https://ninghao.net/video/6693","title":"创建与使用 BLoC：用 Sink 输入数据","videoUrl":"https://ninghao.net/system/dynamics/video/flutter-bloc-01-04-bloc-sink-1412770304.mp4"},{"url":"https://ninghao.net/video/6694","title":"创建与使用 BLoC：用 Stream 输出数据","videoUrl":"https://ninghao.net/system/dynamics/video/flutter-bloc-01-05-bloc-stream-267325939.mp4"}]},{"title":"Flutter\b 移动应用：RxDart","alias":"Flutter：RxDart","url":"https://ninghao.net/course/6665","pathHtml":"./src/ninghao/html/RxDart.html","pathVideo":"./src/ninghao/video/RxDart","children":[{"url":"https://ninghao.net/video/6667","title":"介绍","videoUrl":"https://ninghao.net/system/dynamics/video/flutter-rxdart-00-00-intro-841801688.mp4"},{"url":"https://ninghao.net/video/6668","title":"准备项目","videoUrl":"https://ninghao.net/system/dynamics/video/flutter-rxdart-00-01-prepare-1637747992.mp4"},{"url":"https://ninghao.net/video/6669","title":"创建 RxDartDemo","videoUrl":"https://ninghao.net/system/dynamics/video/flutter-rxdart-00-02-rxdart-demo-1552916683.mp4"},{"url":"https://ninghao.net/video/6670","title":"安装 RxDart 包","videoUrl":"https://ninghao.net/system/dynamics/video/flutter-rxdart-00-03-install-rxdart-786314356.mp4"},{"url":"https://ninghao.net/video/6672","title":"Rx，RxDart，Observable 与 Stream","videoUrl":"https://ninghao.net/system/dynamics/video/flutter-rxdart-01-01-rxdart-intro-1476624125.mp4"},{"url":"https://ninghao.net/video/6673","title":"Observables","videoUrl":"https://ninghao.net/system/dynamics/video/flutter-rxdart-01-02-observable-2103715838.mp4"},{"url":"https://ninghao.net/video/6674","title":"创建 Observables 的几种方法","videoUrl":"https://ninghao.net/system/dynamics/video/flutter-rxdart-01-03-observable-factory-1303124596.mp4"},{"url":"https://ninghao.net/video/6676","title":"使用 Subjects 控制 Observables","videoUrl":"https://ninghao.net/system/dynamics/video/flutter-rxdart-02-01-subjects-143602551.mp4"},{"url":"https://ninghao.net/video/6677","title":"BehaviorSubject","videoUrl":"https://ninghao.net/system/dynamics/video/flutter-rxdart-02-02-behavior-subject-1348595197.mp4"},{"url":"https://ninghao.net/video/6678","title":"ReplaySubject","videoUrl":"https://ninghao.net/system/dynamics/video/flutter-rxdart-02-03-replaysubject-132117006.mp4"},{"url":"https://ninghao.net/video/6680","title":"准备一个文本框往 Observable 上添加数据","videoUrl":"https://ninghao.net/system/dynamics/video/flutter-rxdart-03-01-text-field-subject-730397821.mp4"},{"url":"https://ninghao.net/video/6681","title":"RxDart 的数据转换方法（map）","videoUrl":"https://ninghao.net/system/dynamics/video/flutter-rxdart-03-02-map-151178814.mp4"},{"url":"https://ninghao.net/video/6682","title":"where","videoUrl":"https://ninghao.net/system/dynamics/video/flutter-rxdart-03-03-where-1901856614.mp4"},{"url":"https://ninghao.net/video/6683","title":"debounce","videoUrl":"https://ninghao.net/system/dynamics/video/flutter-rxdart-03-04-debounce-797885410.mp4"}]},{"title":"Flutter\b 移动应用：Stream","alias":"Flutter：Stream","url":"https://ninghao.net/course/6648","pathHtml":"./src/ninghao/html/Stream.html","pathVideo":"./src/ninghao/video/Stream","children":[{"url":"https://ninghao.net/video/6650","title":"介绍","videoUrl":"https://ninghao.net/system/dynamics/video/flutter-stream-00-00-intro-1790809269.mp4"},{"url":"https://ninghao.net/video/6651","title":"准备项目","videoUrl":"https://ninghao.net/system/dynamics/video/flutter-stream-00-01-prepare-1081137086.mp4"},{"url":"https://ninghao.net/video/6652","title":"创建 StreamDemo","videoUrl":"https://ninghao.net/system/dynamics/video/flutter-stream-00-02-stream-demo-1986831871.mp4"},{"url":"https://ninghao.net/video/6654","title":"创建与监听 Stream","videoUrl":"https://ninghao.net/system/dynamics/video/flutter-stream-01-01-create-and-listening-stream-962859804.mp4"},{"url":"https://ninghao.net/video/6655","title":"给 Stream 添加一个订阅（subscription）","videoUrl":"https://ninghao.net/system/dynamics/video/flutter-stream-01-02-add-subscription-to-stream-1667383838.mp4"},{"url":"https://ninghao.net/video/6656","title":"暂停、恢复、取消监听 Stream","videoUrl":"https://ninghao.net/system/dynamics/video/flutter-stream-01-03-pause-resume-stream-1315914273.mp4"},{"url":"https://ninghao.net/video/6658","title":"StreamController：控制 Stream","videoUrl":"https://ninghao.net/system/dynamics/video/flutter-stream-02-01-streamcontroller-2003014445.mp4"},{"url":"https://ninghao.net/video/6659","title":"StreamController：使用 Sink 往 Stream 上添加数据","videoUrl":"https://ninghao.net/system/dynamics/video/flutter-stream-02-02-streamcontroller-sink-510134536.mp4"},{"url":"https://ninghao.net/video/6660","title":"StreamController：创建可以多次订阅的 Broadcast Streams","videoUrl":"https://ninghao.net/system/dynamics/video/flutter-stream-02-03-streamcontroller-boradcast-1347104631.mp4"},{"url":"https://ninghao.net/video/6662","title":"在界面上显示 Stream 上的数据","videoUrl":"https://ninghao.net/system/dynamics/video/flutter-stream-03-01-using-stream-data-944393567.mp4"},{"url":"https://ninghao.net/video/6663","title":"StreamBuilder：根据 Stream 上的数据构建小部件","videoUrl":"https://ninghao.net/system/dynamics/video/flutter-stream-03-02-streambuilder-1602069886.mp4"}]},{"title":"Flutter\b 移动应用：状态管理","alias":"Flutter：State Management","url":"https://ninghao.net/course/6630","pathHtml":"./src/ninghao/html/State Management.html","pathVideo":"./src/ninghao/video/State Management","children":[{"url":"https://ninghao.net/video/6632","title":"介绍","videoUrl":"https://ninghao.net/system/dynamics/video/flutter-state-00-00-intro-1073646824.mp4"},{"url":"https://ninghao.net/video/6633","title":"准备项目","videoUrl":"https://ninghao.net/system/dynamics/video/flutter-state-00-01-prepare-1310881498.mp4"},{"url":"https://ninghao.net/video/6634","title":"创建 StateManagementDemo 小部件","videoUrl":"https://ninghao.net/system/dynamics/video/flutter-state-00-02-state-management-demo-99858860.mp4"},{"url":"https://ninghao.net/video/6636","title":"StatelessWidget：无变化状态的小部件","videoUrl":"https://ninghao.net/system/dynamics/video/flutter-state-01-01-stateless-widget-1118169054.mp4"},{"url":"https://ninghao.net/video/6637","title":"StatefulWidget：带变化状态的小部件","videoUrl":"https://ninghao.net/system/dynamics/video/flutter-state-01-02-stateful-widget-1315626547.mp4"},{"url":"https://ninghao.net/video/6638","title":"状态管理（由父辈管理状态）","videoUrl":"https://ninghao.net/system/dynamics/video/flutter-state-01-03-state-parent-1341786821.mp4"},{"url":"https://ninghao.net/video/6639","title":"从父辈那里传递个回调","videoUrl":"https://ninghao.net/system/dynamics/video/flutter-state-01-04-state-parent-callback-1086699478.mp4"},{"url":"https://ninghao.net/video/6640","title":"小部件树：Widget Tree","videoUrl":"https://ninghao.net/system/dynamics/video/flutter-state-01-05-widget-tree-721572617.mp4"},{"url":"https://ninghao.net/video/6642","title":"InheritedWidget：直接把数据传递给需要的小部件","videoUrl":"https://ninghao.net/system/dynamics/video/flutter-state-02-01-inherited-widget-515109946.mp4"},{"url":"https://ninghao.net/video/6643","title":"创建与使用 InheritedWidget 有效地传递数据给子部件","videoUrl":"https://ninghao.net/system/dynamics/video/flutter-state-02-02-using-inherited-widget-1877989660.mp4"},{"url":"https://ninghao.net/video/6645","title":"ScopedModel：安装与基本用法介绍","videoUrl":"https://ninghao.net/system/dynamics/video/flutter-state-03-01-scoped-model-63741504.mp4"},{"url":"https://ninghao.net/video/6646","title":"使用 ScopedModel 传递数据","videoUrl":"https://ninghao.net/system/dynamics/video/flutter-state-03-02-using-scoped-model-412453383.mp4"}]},{"title":"Flutter\b 移动应用：MDC","alias":"Flutter：MDC","url":"https://ninghao.net/course/6604","pathHtml":"./src/ninghao/html/MDC.html","pathVideo":"./src/ninghao/video/MDC","children":[{"url":"https://ninghao.net/video/6606","title":"介绍","videoUrl":"https://ninghao.net/system/dynamics/video/flutter-mdc4-00-00-intro-80393627.mp4"},{"url":"https://ninghao.net/video/6607","title":"升级 Flutter SDK 后屏幕报错（0.8.1）","videoUrl":"https://ninghao.net/system/dynamics/video/flutter-mdc4-00-01-upgrade-flutter-sdk-393916256.mp4"},{"url":"https://ninghao.net/video/6609","title":"Chip：小碎片","videoUrl":"https://ninghao.net/system/dynamics/video/flutter-mdc4-01-01-chip-388735734.mp4"},{"url":"https://ninghao.net/video/6610","title":"Wrap：换行显示小部件","videoUrl":"https://ninghao.net/system/dynamics/video/flutter-mdc4-01-02-wrap-420669440.mp4"},{"url":"https://ninghao.net/video/6611","title":"Divider：分隔符","videoUrl":"https://ninghao.net/system/dynamics/video/flutter-mdc4-01-03-divider-1907143698.mp4"},{"url":"https://ninghao.net/video/6612","title":"Chip：带删除功能的小碎片","videoUrl":"https://ninghao.net/system/dynamics/video/flutter-mdc4-01-04-chip-with-deleteicon-1391817880.mp4"},{"url":"https://ninghao.net/video/6613","title":"Chip：用列表生成带删除功能的小碎片","videoUrl":"https://ninghao.net/system/dynamics/video/flutter-mdc4-01-05-chip-ondeleted-list-1019475687.mp4"},{"url":"https://ninghao.net/video/6614","title":"ActionChip：动作碎片","videoUrl":"https://ninghao.net/system/dynamics/video/flutter-mdc4-01-06-action-chip-730502173.mp4"},{"url":"https://ninghao.net/video/6615","title":"FilterChip：过滤碎片","videoUrl":"https://ninghao.net/system/dynamics/video/flutter-mdc4-01-07-filter-chip-645266387.mp4"},{"url":"https://ninghao.net/video/6616","title":"ChoiceChip：选择碎片","videoUrl":"https://ninghao.net/system/dynamics/video/flutter-mdc4-01-08-choice-chip-1781213007.mp4"},{"url":"https://ninghao.net/video/6618","title":"DataTable：数据表格","videoUrl":"https://ninghao.net/system/dynamics/video/flutter-mdc4-02-01-datatable-60671271.mp4"},{"url":"https://ninghao.net/video/6619","title":"DataTable：用列表生成数据表格","videoUrl":"https://ninghao.net/system/dynamics/video/flutter-mdc4-02-02-datatable-from-list-1725421342.mp4"},{"url":"https://ninghao.net/video/6620","title":"DataTable：数据表格的排序","videoUrl":"https://ninghao.net/system/dynamics/video/flutter-mdc4-02-03-datatable-sort-2043687447.mp4"},{"url":"https://ninghao.net/video/6621","title":"DataTable：选择数据表格行","videoUrl":"https://ninghao.net/system/dynamics/video/flutter-mdc4-02-04-datatable-selected-366169344.mp4"},{"url":"https://ninghao.net/video/6622","title":"PaginatedDataTable：分页显示表格数据","videoUrl":"https://ninghao.net/system/dynamics/video/flutter-mdc4-02-05-paginated-data-table-1692330886.mp4"},{"url":"https://ninghao.net/video/6623","title":"PaginatedDataTable：排序","videoUrl":"https://ninghao.net/system/dynamics/video/flutter-mdc4-02-06-paginated-data-table-sort-410867504.mp4"},{"url":"https://ninghao.net/video/6625","title":"Card：卡片","videoUrl":"https://ninghao.net/system/dynamics/video/flutter-mdc4-03-01-card-604749636.mp4"},{"url":"https://ninghao.net/video/6626","title":"ClipRRect：圆角（给图像添加圆角效果）","videoUrl":"https://ninghao.net/system/dynamics/video/flutter-mdc4-03-02-cliprrect-486761709.mp4"},{"url":"https://ninghao.net/video/6628","title":"Stepper：步骤","videoUrl":"https://ninghao.net/system/dynamics/video/flutter-mdc4-04-01-stepper-2088217692.mp4"},{"url":"https://ninghao.net/video/6629","title":"Stepper：步骤的行为","videoUrl":"https://ninghao.net/system/dynamics/video/flutter-mdc4-04-02-stepper-behavior-33154656.mp4"}]},{"title":"Flutter\b 移动应用：对话框","alias":"Flutter：Modal","url":"https://ninghao.net/course/6584","pathHtml":"./src/ninghao/html/Modal.html","pathVideo":"./src/ninghao/video/Modal","children":[{"url":"https://ninghao.net/video/6586","title":"SimpleDialog：显示对话框（showDialog）","videoUrl":"https://ninghao.net/system/dynamics/video/flutter-mdc3-01-01-simpledialog-1458008628.mp4"},{"url":"https://ninghao.net/video/6587","title":"SimpleDialog：选项（SimpleDialogOption）","videoUrl":"https://ninghao.net/system/dynamics/video/flutter-mdc3-01-02-simpledialog-option-1318850319.mp4"},{"url":"https://ninghao.net/video/6588","title":"SimpleDialog：获取与使用选项的值","videoUrl":"https://ninghao.net/system/dynamics/video/flutter-mdc3-01-03-option-value-158479225.mp4"},{"url":"https://ninghao.net/video/6590","title":"AlertDialog：提示对话框","videoUrl":"https://ninghao.net/system/dynamics/video/flutter-mdc3-02-01-alert-dialog-1220053057.mp4"},{"url":"https://ninghao.net/video/6591","title":"AlertDialog：获取与使用动作的值","videoUrl":"https://ninghao.net/system/dynamics/video/flutter-mdc3-02-02-alert-dialog-value-643921254.mp4"},{"url":"https://ninghao.net/video/6593","title":"BottomSheet：底部滑动窗口","videoUrl":"https://ninghao.net/system/dynamics/video/flutter-mdc3-03-01-bottom-sheet-967030191.mp4"},{"url":"https://ninghao.net/video/6594","title":"BottomSheet：对话框式底部滑动窗口（showModalBottomSheet）","videoUrl":"https://ninghao.net/system/dynamics/video/flutter-mdc3-03-02-show-modal-bottom-sheet-299756940.mp4"},{"url":"https://ninghao.net/video/6595","title":"处理使用对话框式底部滑动窗口的数据","videoUrl":"https://ninghao.net/system/dynamics/video/flutter-mdc3-03-03-show-modal-bottom-sheet-data-355048314.mp4"},{"url":"https://ninghao.net/video/6597","title":"SnackBar：操作提示栏","videoUrl":"https://ninghao.net/system/dynamics/video/flutter-mdc3-04-01-snackbar-1241862621.mp4"},{"url":"https://ninghao.net/video/6599","title":"ExpansionPanel：收缩面板","videoUrl":"https://ninghao.net/system/dynamics/video/flutter-mdc3-05-01-expansion-panel-1812372174.mp4"},{"url":"https://ninghao.net/video/6600","title":"ExpansionPanel：面板的收起与展开","videoUrl":"https://ninghao.net/system/dynamics/video/flutter-mdc3-05-02-expansion-panel-isexpanded-859264395.mp4"},{"url":"https://ninghao.net/video/6601","title":"ExpansionPanel：面板列表项目","videoUrl":"https://ninghao.net/system/dynamics/video/flutter-mdc3-05-03-expansion-item-1252191211.mp4"}]},{"title":"Flutter\b 移动应用：按钮","alias":"Flutter：Buttons","url":"https://ninghao.net/course/6561","pathHtml":"./src/ninghao/html/Buttons.html","pathVideo":"./src/ninghao/video/Buttons","children":[{"url":"https://ninghao.net/video/6563","title":"介绍","videoUrl":"https://ninghao.net/system/dynamics/video/flutter-mdc-00-00-intro-2020846996.mp4"},{"url":"https://ninghao.net/video/6564","title":"准备项目","videoUrl":"https://ninghao.net/system/dynamics/video/flutter-mdc-00-01-prepare-237526694.mp4"},{"url":"https://ninghao.net/video/6565","title":"VS Code：自定义代码片断","videoUrl":"https://ninghao.net/system/dynamics/video/flutter-mdc-00-02-vscode-custom-snippets-100355803.mp4"},{"url":"https://ninghao.net/video/6566","title":"准备 Material Components 演示页面","videoUrl":"https://ninghao.net/system/dynamics/video/flutter-mdc-00-03-material-components-page-857888223.mp4"},{"url":"https://ninghao.net/video/6568","title":"FloatingActionButton：漂浮动作按钮","videoUrl":"https://ninghao.net/system/dynamics/video/flutter-mdc-01-01-floating-action-button-1619584966.mp4"},{"url":"https://ninghao.net/video/6569","title":"BottomAppBar：底部工具栏","videoUrl":"https://ninghao.net/system/dynamics/video/flutter-mdc-01-02-bottom-app-bar-1170583789.mp4"},{"url":"https://ninghao.net/video/6571","title":"创建演示小部件用的页面","videoUrl":"https://ninghao.net/system/dynamics/video/flutter-mdc-02-01-button-demo-2065513694.mp4"},{"url":"https://ninghao.net/video/6572","title":"FlatButton：文字按钮","videoUrl":"https://ninghao.net/system/dynamics/video/flutter-mdc-02-02-flatbutton-160164319.mp4"},{"url":"https://ninghao.net/video/6573","title":"RaisedButton：按钮","videoUrl":"https://ninghao.net/system/dynamics/video/flutter-mdc-02-03-raisedbutton-303465875.mp4"},{"url":"https://ninghao.net/video/6574","title":"按钮主题：颜色、形状","videoUrl":"https://ninghao.net/system/dynamics/video/flutter-mdc-02-04-button-theme-354095492.mp4"},{"url":"https://ninghao.net/video/6575","title":"OutlineButton：描边按钮","videoUrl":"https://ninghao.net/system/dynamics/video/flutter-mdc-02-05-outline-button-1108731595.mp4"},{"url":"https://ninghao.net/video/6576","title":"按钮容器 Container：有固定宽度的按钮","videoUrl":"https://ninghao.net/system/dynamics/video/flutter-mdc-02-06-button-container-1843376723.mp4"},{"url":"https://ninghao.net/video/6577","title":"按钮容器 Expanded：占满可用宽度的按钮","videoUrl":"https://ninghao.net/system/dynamics/video/flutter-mdc-02-07-expanded-button-1102276267.mp4"},{"url":"https://ninghao.net/video/6578","title":"按钮容器 ButtonBar：一组带边距的横排显示按钮","videoUrl":"https://ninghao.net/system/dynamics/video/flutter-mdc-02-08-buttonbar-133031033.mp4"},{"url":"https://ninghao.net/video/6579","title":"整理：把演示放在单独的文件里","videoUrl":"https://ninghao.net/system/dynamics/video/flutter-mdc-02-09-button-demo-1371857660.mp4"},{"url":"https://ninghao.net/video/6581","title":"准备 PopupMenuButtonDemo","videoUrl":"https://ninghao.net/system/dynamics/video/flutter-mdc-03-01-popup-menu-button-demo-1958002574.mp4"},{"url":"https://ninghao.net/video/6582","title":"PopupMenuButton：弹出式菜单按钮","videoUrl":"https://ninghao.net/system/dynamics/video/flutter-mdc-03-02-popup-menu-button-91836328.mp4"}]},{"title":"Flutter\b 移动应用：表单","alias":"Flutter：Forms","url":"https://ninghao.net/course/6544","pathHtml":"./src/ninghao/html/Forms.html","pathVideo":"./src/ninghao/video/Forms","children":[{"url":"https://ninghao.net/video/6546","title":"介绍","videoUrl":"https://ninghao.net/system/dynamics/video/flutter-forms-00-00-intro-182498479.mp4"},{"url":"https://ninghao.net/video/6547","title":"准备项目","videoUrl":"https://ninghao.net/system/dynamics/video/flutter-forms-00-01-prepare-1187239970.mp4"},{"url":"https://ninghao.net/video/6548","title":"创建 FormDemo 小部件","videoUrl":"https://ninghao.net/system/dynamics/video/flutter-forms-00-02-form-demo-1513224640.mp4"},{"url":"https://ninghao.net/video/6549","title":"Theme：定制、使用、重置、覆盖主题","videoUrl":"https://ninghao.net/system/dynamics/video/flutter-forms-00-03-theme-74624611.mp4"},{"url":"https://ninghao.net/video/6551","title":"TextField：文本字段","videoUrl":"https://ninghao.net/system/dynamics/video/flutter-forms-01-01-textfield-1631423601.mp4"},{"url":"https://ninghao.net/video/6552","title":"TextField：文本字段样式（InputDecoration）","videoUrl":"https://ninghao.net/system/dynamics/video/flutter-forms-01-02-inputdecoration-1384659206.mp4"},{"url":"https://ninghao.net/video/6553","title":"TextField：监视文本字段的值的变化与提交","videoUrl":"https://ninghao.net/system/dynamics/video/flutter-forms-01-03-textfield-onchanged-onsubmitted-1440402849.mp4"},{"url":"https://ninghao.net/video/6554","title":"TextField：使用 TextEditingController 监听文本字段变化","videoUrl":"https://ninghao.net/system/dynamics/video/flutter-forms-01-04-text-editing-controller-449822382.mp4"},{"url":"https://ninghao.net/video/6556","title":"Form：表单","videoUrl":"https://ninghao.net/system/dynamics/video/flutter-forms-02-01-form-2130948006.mp4"},{"url":"https://ninghao.net/video/6557","title":"Form：保存与获取表单里的数据","videoUrl":"https://ninghao.net/system/dynamics/video/flutter-forms-02-02-form-state-2106893811.mp4"},{"url":"https://ninghao.net/video/6558","title":"Form：验证表单里的数据","videoUrl":"https://ninghao.net/system/dynamics/video/flutter-forms-02-03-form-validate-1484820392.mp4"},{"url":"https://ninghao.net/video/6559","title":"Form：自动验证","videoUrl":"https://ninghao.net/system/dynamics/video/flutter-forms-02-04-form-autovalidate-168643688.mp4"},{"url":"https://ninghao.net/video/6560","title":"SnackBar：在屏幕底部动画弹出提示栏","videoUrl":"https://ninghao.net/system/dynamics/video/flutter-forms-02-05-snackbar-155717094.mp4"}]},{"title":"Flutter\b 移动应用：路由","alias":"Flutter：Routes","url":"https://ninghao.net/course/6530","pathHtml":"./src/ninghao/html/Routes.html","pathVideo":"./src/ninghao/video/Routes","children":[{"url":"https://ninghao.net/video/6532","title":"介绍","videoUrl":"https://ninghao.net/system/dynamics/video/flutter-routes-00-00-intro-1527835643.mp4"},{"url":"https://ninghao.net/video/6533","title":"准备项目","videoUrl":"https://ninghao.net/system/dynamics/video/flutter-routes-00-01-prepare-1933883703.mp4"},{"url":"https://ninghao.net/video/6534","title":"VS Code：Flutter 代码片断","videoUrl":"https://ninghao.net/system/dynamics/video/flutter-routes-00-02-flutter-snippets-948847756.mp4"},{"url":"https://ninghao.net/video/6536","title":"一堆路由","videoUrl":"https://ninghao.net/system/dynamics/video/flutter-routes-01-01-stack-1854110887.mp4"},{"url":"https://ninghao.net/video/6537","title":"打开新页面并返回（push 与 pop）：准备","videoUrl":"https://ninghao.net/system/dynamics/video/flutter-routes-01-02-push-pop-prepare-1465025456.mp4"},{"url":"https://ninghao.net/video/6538","title":"打开新页面并返回（push 与 pop）：实施","videoUrl":"https://ninghao.net/system/dynamics/video/flutter-routes-01-03-push-pop-2025523568.mp4"},{"url":"https://ninghao.net/video/6539","title":"带名字的路由（ Navigator.pushNamed）","videoUrl":"https://ninghao.net/system/dynamics/video/flutter-routes-01-04-named-route-1749677420.mp4"},{"url":"https://ninghao.net/video/6540","title":"初始路由：initialRoute","videoUrl":"https://ninghao.net/system/dynamics/video/flutter-routes-01-05-initialroute-571583600.mp4"},{"url":"https://ninghao.net/video/6542","title":"InkWell：添加溅墨动画效果","videoUrl":"https://ninghao.net/system/dynamics/video/flutter-routes-02-01-inkwell-247613787.mp4"},{"url":"https://ninghao.net/video/6543","title":"在内容详情页上显示内容","videoUrl":"https://ninghao.net/system/dynamics/video/flutter-routes-02-02-post-show-854342003.mp4"}]},{"title":"VS Code：源代码管理","alias":"Vs Code: Source Code Management","url":"https://ninghao.net/course/6523"},{"title":"Flutter\b 移动应用：Sliver","alias":"Flutter：Sliver","url":"https://ninghao.net/course/6510","pathHtml":"./src/ninghao/html/Sliver.html","pathVideo":"./src/ninghao/video/Sliver","children":[{"url":"https://ninghao.net/video/6512","title":"介绍","videoUrl":"https://ninghao.net/system/dynamics/video/flutter-sliver-00-00-intro-740369387.mp4"},{"url":"https://ninghao.net/video/6513","title":"准备项目","videoUrl":"https://ninghao.net/system/dynamics/video/flutter-sliver-00-01-prepare-277936382.mp4"},{"url":"https://ninghao.net/video/6514","title":"创建 SliverDemo 小部件","videoUrl":"https://ninghao.net/system/dynamics/video/flutter-sliver-00-02-sliver-demo-476922401.mp4"},{"url":"https://ninghao.net/video/6516","title":"Slivers","videoUrl":"https://ninghao.net/system/dynamics/video/flutter-sliver-01-01-sliver-480299332.mp4"},{"url":"https://ninghao.net/video/6517","title":"SliverGrid：网格视图","videoUrl":"https://ninghao.net/system/dynamics/video/flutter-sliver-01-02-sliver-grid-31856473.mp4"},{"url":"https://ninghao.net/video/6518","title":"SliverPadding（内边距） 与 SliverSafeArea（安全区）","videoUrl":"https://ninghao.net/system/dynamics/video/flutter-sliver-01-03-sliverpadding-sliversafearea-974377558.mp4"},{"url":"https://ninghao.net/video/6519","title":"SliverList：列表视图","videoUrl":"https://ninghao.net/system/dynamics/video/flutter-sliver-01-04-sliver-list-30610743.mp4"},{"url":"https://ninghao.net/video/6520","title":"SliverAppBar：应用工具栏","videoUrl":"https://ninghao.net/system/dynamics/video/flutter-sliver-01-05-sliver-app-bar-361199574.mp4"},{"url":"https://ninghao.net/video/6521","title":"带渐近动画的可伸缩空间","videoUrl":"https://ninghao.net/system/dynamics/video/flutter-sliver-01-06-flexible-space-bar-291663750.mp4"}]},{"title":"VS Code：编辑技巧","alias":"Vs Code: Editing","url":"https://ninghao.net/course/6490"},{"title":"Flutter\b 移动应用：视图","alias":"Flutter：Views","url":"https://ninghao.net/course/6475","pathHtml":"./src/ninghao/html/Views.html","pathVideo":"./src/ninghao/video/Views","children":[{"url":"https://ninghao.net/video/6477","title":"介绍","videoUrl":"https://ninghao.net/system/dynamics/video/flutter-view-00-00-intro-346364088.mp4"},{"url":"https://ninghao.net/video/6478","title":"升级 Flutter SDK 与项目用的 Packages","videoUrl":"https://ninghao.net/system/dynamics/video/flutter-view-00-01-upgrade-flutter-232496989.mp4"},{"url":"https://ninghao.net/video/6479","title":"准备项目","videoUrl":"https://ninghao.net/system/dynamics/video/flutter-view-00-02-prepare-1109058448.mp4"},{"url":"https://ninghao.net/video/6480","title":"创建 ViewDemo 小部件","videoUrl":"https://ninghao.net/system/dynamics/video/flutter-view-00-03-view-demo-widget-371078100.mp4"},{"url":"https://ninghao.net/video/6482","title":"PageView：页面视图","videoUrl":"https://ninghao.net/system/dynamics/video/flutter-view-01-01-page-view-1056974892.mp4"},{"url":"https://ninghao.net/video/6483","title":"PageView：页面视图的属性","videoUrl":"https://ninghao.net/system/dynamics/video/flutter-view-01-02-page-view-prop-1954584764.mp4"},{"url":"https://ninghao.net/video/6484","title":"PageView：用 PageController 调整页面的显示","videoUrl":"https://ninghao.net/system/dynamics/video/flutter-view-01-03-page-view-controller-524409778.mp4"},{"url":"https://ninghao.net/video/6485","title":"PageView.builder 按需生成页面","videoUrl":"https://ninghao.net/system/dynamics/video/flutter-view-01-04-page-view-builder-1426730928.mp4"},{"url":"https://ninghao.net/video/6487","title":"GridView：网格视图（GridView.count）","videoUrl":"https://ninghao.net/system/dynamics/video/flutter-view-02-01-gridview-318016574.mp4"},{"url":"https://ninghao.net/video/6488","title":"GridView.extent","videoUrl":"https://ninghao.net/system/dynamics/video/flutter-view-02-02-gridview-extent-1470691593.mp4"},{"url":"https://ninghao.net/video/6489","title":"GridView.builder 按需生成视图项目","videoUrl":"https://ninghao.net/system/dynamics/video/flutter-view-02-03-gridview-builder-945670103.mp4"}]},{"title":"Redis：数据存储","alias":"Redis: Data Store","url":"https://ninghao.net/course/6465"},{"title":"Flutter\b 移动应用：布局","alias":"Flutter：Layouts","url":"https://ninghao.net/course/6448","pathHtml":"./src/ninghao/html/Layouts.html","pathVideo":"./src/ninghao/video/Layouts","children":[{"url":"https://ninghao.net/video/6450","title":"介绍","videoUrl":"https://ninghao.net/system/dynamics/video/flutter-layout-00-00-intro-2011139917.mp4"},{"url":"https://ninghao.net/video/6451","title":"准备项目","videoUrl":"https://ninghao.net/system/dynamics/video/flutter-layout-00-01-prepare-1238546849.mp4"},{"url":"https://ninghao.net/video/6452","title":"创建 LayoutDemo 小部件","videoUrl":"https://ninghao.net/system/dynamics/video/flutter-layout-00-02-layout-demo-widget-305587148.mp4"},{"url":"https://ninghao.net/video/6453","title":"创建可配置的图标徽章（IconBadge）小部件","videoUrl":"https://ninghao.net/system/dynamics/video/flutter-layout-00-03-iconbadge-widget-976048996.mp4"},{"url":"https://ninghao.net/video/6455","title":"Row（横排） 与 Column（竖排）","videoUrl":"https://ninghao.net/system/dynamics/video/flutter-layout-01-01-row-and-column-521493705.mp4"},{"url":"https://ninghao.net/video/6456","title":"mainAxis：主轴","videoUrl":"https://ninghao.net/system/dynamics/video/flutter-layout-01-02-mainaxis-1063089459.mp4"},{"url":"https://ninghao.net/video/6457","title":"crossAxis：交叉轴","videoUrl":"https://ninghao.net/system/dynamics/video/flutter-layout-01-03-crossaxis-1854919642.mp4"},{"url":"https://ninghao.net/video/6458","title":"SizedBox：固定尺寸的盒子","videoUrl":"https://ninghao.net/system/dynamics/video/flutter-layout-02-01-sizedbox-1228391517.mp4"},{"url":"https://ninghao.net/video/6459","title":"Alignment：对齐","videoUrl":"https://ninghao.net/system/dynamics/video/flutter-layout-02-02-alignment-162151744.mp4"},{"url":"https://ninghao.net/video/6460","title":"Stack：一摞小部件","videoUrl":"https://ninghao.net/system/dynamics/video/flutter-layout-02-03-stack-805708834.mp4"},{"url":"https://ninghao.net/video/6461","title":"AspectRatio：宽高比","videoUrl":"https://ninghao.net/system/dynamics/video/flutter-layout-02-04-aspect-ratio-991060781.mp4"},{"url":"https://ninghao.net/video/6462","title":"ConstrainedBox：带限制的盒子","videoUrl":"https://ninghao.net/system/dynamics/video/flutter-layout-02-05-constrained-box-1744950205.mp4"}]},{"title":"Flutter\b 移动应用：基础部件","alias":"Flutter：Basic Widgets","url":"https://ninghao.net/course/6430","pathHtml":"./src/ninghao/html/Basic Widgets.html","pathVideo":"./src/ninghao/video/Basic Widgets","children":[{"url":"https://ninghao.net/video/6432","title":"介绍","videoUrl":"https://ninghao.net/system/dynamics/video/flutter-basic-00-00-intro-1504469724.mp4"},{"url":"https://ninghao.net/video/6433","title":"准备项目","videoUrl":"https://ninghao.net/system/dynamics/video/flutter-basic-00-01-prepare-417010087.mp4"},{"url":"https://ninghao.net/video/6435","title":"查看小部件的定义","videoUrl":"https://ninghao.net/system/dynamics/video/flutter-basic-01-01-dig-into-widget-551281315.mp4"},{"url":"https://ninghao.net/video/6436","title":"Text：文字与文字样式","videoUrl":"https://ninghao.net/system/dynamics/video/flutter-basic-01-02-text-textstyle-2060461813.mp4"},{"url":"https://ninghao.net/video/6437","title":"RichText：行内多样式的文字","videoUrl":"https://ninghao.net/system/dynamics/video/flutter-basic-01-03-richtext-1279127337.mp4"},{"url":"https://ninghao.net/video/6439","title":"Container：容器","videoUrl":"https://ninghao.net/system/dynamics/video/flutter-basic-01-04-container-1129358673.mp4"},{"url":"https://ninghao.net/video/6440","title":"BoxDecoration：装饰盒子","videoUrl":"https://ninghao.net/system/dynamics/video/flutter-basic-01-05-box-decoration-1555096532.mp4"},{"url":"https://ninghao.net/video/6441","title":"BoxDecoration：边框（border）","videoUrl":"https://ninghao.net/system/dynamics/video/flutter-basic-01-06-box-decoration-border-793754920.mp4"},{"url":"https://ninghao.net/video/6442","title":"BoxDecoration：圆角（borderRadius）","videoUrl":"https://ninghao.net/system/dynamics/video/flutter-basic-01-07-box-decoration-border-radius-915607463.mp4"},{"url":"https://ninghao.net/video/6443","title":"BoxDecoration：阴影（borderShadow）","videoUrl":"https://ninghao.net/system/dynamics/video/flutter-basic-01-08-box-decoration-border-shadow-1334694882.mp4"},{"url":"https://ninghao.net/video/6444","title":"BoxDecoration：形状（shape）","videoUrl":"https://ninghao.net/system/dynamics/video/flutter-basic-01-09-box-decoration-shape-198212663.mp4"},{"url":"https://ninghao.net/video/6445","title":"BoxDecoration：渐变（gradient）","videoUrl":"https://ninghao.net/system/dynamics/video/flutter-basic-01-10-box-decoration-gradient-2011587364.mp4"},{"url":"https://ninghao.net/video/6446","title":"BoxDecoration：背景图像（image）","videoUrl":"https://ninghao.net/system/dynamics/video/flutter-basic-01-11-box-decoration-image-407692988.mp4"}]},{"title":"Nest.js：应用框架","alias":"Nest.js：Web Framework","url":"https://ninghao.net/course/6416"},{"title":"Flutter 移动应用：界面结构","alias":"\bFlutter App：Scaffold","url":"https://ninghao.net/course/6393","pathHtml":"./src/ninghao/html/Scaffold.html","pathVideo":"./src/ninghao/video/Scaffold","children":[{"url":"https://ninghao.net/video/6395","title":"介绍","videoUrl":"https://ninghao.net/system/dynamics/video/flutter-structure-00-00-intro-2059216979.mp4"},{"url":"https://ninghao.net/video/6396","title":"准备项目","videoUrl":"https://ninghao.net/system/dynamics/video/flutter-structure-00-01-prepare-930952907.mp4"},{"url":"https://ninghao.net/video/6398","title":"Material 应用","videoUrl":"https://ninghao.net/system/dynamics/video/flutter-structure-01-01-material-app-1558934810.mp4"},{"url":"https://ninghao.net/video/6399","title":"AppBar：工具栏上的图标按钮（IconButton）","videoUrl":"https://ninghao.net/system/dynamics/video/flutter-structure-01-02-appbar-iconbutton-1392394271.mp4"},{"url":"https://ninghao.net/video/6400","title":"TabBar：用标签形式展示内容","videoUrl":"https://ninghao.net/system/dynamics/video/flutter-structure-01-03-tabbar-1087517450.mp4"},{"url":"https://ninghao.net/video/6401","title":"TabBar：自定义标签栏的样式","videoUrl":"https://ninghao.net/system/dynamics/video/flutter-structure-01-04-tabbar-style-2110096287.mp4"},{"url":"https://ninghao.net/video/6402","title":"Material：自定义按钮水波纹样式","videoUrl":"https://ninghao.net/system/dynamics/video/flutter-structure-01-05-splash-button-style-1753955973.mp4"},{"url":"https://ninghao.net/video/6404","title":"Drawer：抽屉（边栏）","videoUrl":"https://ninghao.net/system/dynamics/video/flutter-structure-01-06-drawer-198545816.mp4"},{"url":"https://ninghao.net/video/6405","title":"Drawer：在抽屉里使用 ListView， DrawerHeader，ListTile","videoUrl":"https://ninghao.net/system/dynamics/video/flutter-structure-01-07-drawer-listview-1506502524.mp4"},{"url":"https://ninghao.net/video/6406","title":"Drawer：抽屉的打开与关闭","videoUrl":"https://ninghao.net/system/dynamics/video/flutter-structure-01-08-drawer-pop-558982605.mp4"},{"url":"https://ninghao.net/video/6407","title":"UserAccountDrawerHeader：抽屉里的用户帐号信息","videoUrl":"https://ninghao.net/system/dynamics/video/flutter-structure-01-09-useraccountsdrawerheader-1613324862.mp4"},{"url":"https://ninghao.net/video/6408","title":"用户帐户头部的背景图像","videoUrl":"https://ninghao.net/system/dynamics/video/flutter-structure-01-10-decoration-image-15612288.mp4"},{"url":"https://ninghao.net/video/6409","title":"创建 DrawerDemo 小部件","videoUrl":"https://ninghao.net/system/dynamics/video/flutter-structure-01-11-drawer-demo-1534128605.mp4"},{"url":"https://ninghao.net/video/6411","title":"BottomNavigationBar：底部导航栏","videoUrl":"https://ninghao.net/system/dynamics/video/flutter-structure-01-12-bottomnavigrationbar-1702319972.mp4"},{"url":"https://ninghao.net/video/6412","title":"BottomNavigationBar：底部导航栏的激活状态","videoUrl":"https://ninghao.net/system/dynamics/video/flutter-structure-01-13-currentindex-1900007943.mp4"},{"url":"https://ninghao.net/video/6413","title":"StatefulWidget：有状态的小部件","videoUrl":"https://ninghao.net/system/dynamics/video/flutter-structure-01-14-statefulwidget-1198133922.mp4"}]},{"title":"Flutter\b 移动应用：快速起步","alias":"Flutter：Getting Started","url":"https://ninghao.net/course/6376","pathHtml":"./src/ninghao/html/Getting Started.html","pathVideo":"./src/ninghao/video/Getting Started","children":[{"url":"https://ninghao.net/video/6378","title":"介绍","videoUrl":"https://ninghao.net/system/dynamics/video/flutter-preview-00-00-intro-509588527.mp4"},{"url":"https://ninghao.net/video/6379","title":"准备项目","videoUrl":"https://ninghao.net/system/dynamics/video/flutter-preview-00-01-prepare-322161641.mp4"},{"url":"https://ninghao.net/video/6381","title":"在屏幕中间显示 “hello”","videoUrl":"https://ninghao.net/system/dynamics/video/flutter-preview-01-01-hello-world-573093832.mp4"},{"url":"https://ninghao.net/video/6382","title":"自定义小部件（Widget）","videoUrl":"https://ninghao.net/system/dynamics/video/flutter-preview-01-02-custom-widget-1443980025.mp4"},{"url":"https://ninghao.net/video/6383","title":"文字的样式：TextStyle","videoUrl":"https://ninghao.net/system/dynamics/video/flutter-preview-01-03-text-style-1317693725.mp4"},{"url":"https://ninghao.net/video/6384","title":"MaterialApp：使用界面组件与定制界面主题","videoUrl":"https://ninghao.net/system/dynamics/video/flutter-preview-01-04-material-app-1342117153.mp4"},{"url":"https://ninghao.net/video/6386","title":"列表：准备数据","videoUrl":"https://ninghao.net/system/dynamics/video/flutter-preview-02-01-listdata-150199023.mp4"},{"url":"https://ninghao.net/video/6387","title":"列表视图：ListView.builder","videoUrl":"https://ninghao.net/system/dynamics/video/flutter-preview-02-02-listview-890061239.mp4"},{"url":"https://ninghao.net/video/6388","title":"列表项目","videoUrl":"https://ninghao.net/system/dynamics/video/flutter-preview-02-03-listview-item-224170200.mp4"}]},{"title":"Flutter 移动应用：开发准备","alias":"Flutter：Development Env","url":"https://ninghao.net/course/6360","pathHtml":"./src/ninghao/html/Development Env.html","pathVideo":"./src/ninghao/video/Development Env","children":[{"url":"https://ninghao.net/video/6362","title":"介绍","videoUrl":"https://ninghao.net/system/dynamics/video/flutter-00-00-intro-266099909.mp4"},{"url":"https://ninghao.net/video/6364","title":"安装 Flutter SDK（macOS）","videoUrl":"https://ninghao.net/system/dynamics/video/flutter-00-01-install-flutter-sdk-923338034.mp4"},{"url":"https://ninghao.net/video/6365","title":"配置 iOS 开发环境（macOS）","videoUrl":"https://ninghao.net/system/dynamics/video/flutter-00-02-xcode-2061821292.mp4"},{"url":"https://ninghao.net/video/6366","title":"配置 VS Code 代码编辑器","videoUrl":"https://ninghao.net/system/dynamics/video/flutter-00-03-vs-code-1733942749.mp4"},{"url":"https://ninghao.net/video/6367","title":"配置 Android 开发环境（macOS）","videoUrl":"https://ninghao.net/system/dynamics/video/flutter-00-04-install-android-studio-1563917709.mp4"},{"url":"https://ninghao.net/video/6368","title":"检测问题：flutter doctor","videoUrl":"https://ninghao.net/system/dynamics/video/flutter-00-05-flutter-doctor-1007148816.mp4"},{"url":"https://ninghao.net/video/6370","title":"Flutter 在中国地区的特别设置（macOS）","videoUrl":"https://ninghao.net/system/dynamics/video/flutter-01-01-china-flutter-1306310450.mp4"},{"url":"https://ninghao.net/video/6371","title":"创建 Flutter 项目","videoUrl":"https://ninghao.net/system/dynamics/video/flutter-01-02-create-project-752108517.mp4"},{"url":"https://ninghao.net/video/6372","title":"运行 Flutter 项目（iOS 模拟器）","videoUrl":"https://ninghao.net/system/dynamics/video/flutter-01-03-run-project-2023206938.mp4"},{"url":"https://ninghao.net/video/6373","title":"在 Android 模拟器上运行 Flutter 项目","videoUrl":"https://ninghao.net/system/dynamics/video/flutter-01-04-android-studio-avd-1891137560.mp4"}]},{"title":"VS Code：编辑器","alias":"Visual Studio Code","url":"https://ninghao.net/course/6330"},{"title":"Node.js 应用：Ioc Container","alias":"Node.js App：Ioc Container","url":"https://ninghao.net/course/6339"},{"title":"Node.js 应用：权限控制 #2","alias":"Node.js App：ACL #2","url":"https://ninghao.net/course/6313"},{"title":"Egg.js：企业级应用框架","alias":"Egg.js：Enterprise Application Framework","url":"https://ninghao.net/course/6284"},{"title":"Node.js 应用：权限控制","alias":"Node.js App：ACL","url":"https://ninghao.net/course/6268"},{"title":"Node.js 应用：测试","alias":"Node.js App：Testing","url":"https://ninghao.net/course/6250"},{"title":"Node.js 应用：重构与改进 #3","alias":"Node.js App：Refactor #3","url":"https://ninghao.net/course/6230"},{"title":"Node.js 应用：WebSocket","alias":"Node.js App：WebSocket","url":"https://ninghao.net/course/6212"},{"title":"Node.js 应用：国际化","alias":"Node.js App：Internationalization","url":"https://ninghao.net/course/6190"},{"title":"Node.js 应用：邮件验证","alias":"Node.js App：Email Verification","url":"https://ninghao.net/course/6173"},{"title":"Node.js 应用：用户帐号","alias":"Node.js App：Account","url":"https://ninghao.net/course/6154"},{"title":"Node.js 应用：中间件与异常","alias":"Node.js App：Middleware & Exception","url":"https://ninghao.net/course/6138"},{"title":"Node.js 应用：重构与改进 #2","alias":"Node.js App：Refactor #2","url":"https://ninghao.net/course/6119"},{"title":"Node.js 应用：邮件","alias":"Node.js App：Mail","url":"https://ninghao.net/course/6104"},{"title":"Node.js 应用：分页器","alias":"Node.js App：Pagination","url":"https://ninghao.net/course/6084"},{"title":"Node.js 应用：文件系统","alias":"Node.js App：File System","url":"https://ninghao.net/course/6069"},{"title":"Node.js 应用：文件上传","alias":"Node.js App：File upload","url":"https://ninghao.net/course/6053"},{"title":"Node.js 应用：\b身份验证","alias":"Node.js App：Auth","url":"https://ninghao.net/course/6039"},{"title":"Node.js 应用：重构与改进 #1","alias":"Node.js App：Refactor #1","url":"https://ninghao.net/course/6012"},{"title":"Node.js 应用：用户注册","alias":"Node.js App：User Register","url":"https://ninghao.net/course/5996"},{"title":"Node.js 应用：内容关系 #2","alias":"Node.js App：Relationship #2","url":"https://ninghao.net/course/5979"},{"title":"Node.js 应用：\b内容关系","alias":"Node.js App：Relationship","url":"https://ninghao.net/course/5960"},{"title":"Node.js 应用：\b模型","alias":"Node.js App：Models","url":"https://ninghao.net/course/5945"},{"title":"Node.js 应用：查询构建器","alias":"Node.js App：Query Builder","url":"https://ninghao.net/course/5928"},{"title":"Node.js 应用：数据库迁移","alias":"Node.js App：Database Migration","url":"https://ninghao.net/course/5914"},{"title":"支付宝：电脑与手机网站支付","alias":"Alipay","url":"https://ninghao.net/course/5889"},{"title":"关系型数据库","alias":"RDBMS","url":"https://ninghao.net/course/5868"},{"title":"Node.js 应用：视图","alias":"Node.js App：Views","url":"https://ninghao.net/course/5847"},{"title":"网页设计案例：\b页内导航","alias":"Page Design：Sub Navbar","url":"https://ninghao.net/course/4915"},{"title":"网页设计案例：产品页参数","alias":"Page Design：Product Spec","url":"https://ninghao.net/course/4914"},{"title":"网页设计案例：产品页故事区","alias":"Page Design：Product Story","url":"https://ninghao.net/course/4913"},{"title":"网页设计案例：\b产品页","alias":"Page Design：Product","url":"https://ninghao.net/course/4895"},{"title":"网页设计案例：\b页底","alias":"Page Design：Bottom","url":"https://ninghao.net/course/4883"},{"title":"网页设计案例：\b故事区","alias":"Page Design：Story","url":"https://ninghao.net/course/4859"},{"title":"网页设计案例：\b卡片组件","alias":"Page Design：Cards","url":"https://ninghao.net/course/4844"},{"title":"网页设计案例：\b\b旋转木马","alias":"Page Design：Carousel","url":"https://ninghao.net/course/4828"},{"title":"网页设计案例：\b英雄区","alias":"Page Design：Hero","url":"https://ninghao.net/course/4811"},{"title":"网页设计案例：移动导航","alias":"Page Design：Mobile Navigation","url":"https://ninghao.net/course/4792"},{"title":"网页设计案例：导航栏","alias":"Page Design：Navigation","url":"https://ninghao.net/course/4743"},{"title":"网页设计案例：导航设计","alias":"Page Design: Navigation","url":"https://ninghao.net/course/4727"},{"title":"网页设计案例：线框图","alias":"Page Design: Wireframe","url":"https://ninghao.net/course/4707"},{"title":"网页设计案例：工作流","alias":"Page Design: Workflow","url":"https://ninghao.net/course/4688"},{"title":"Node.js 应用：请求与响应","alias":"Node.js App：Request & Response","url":"https://ninghao.net/course/5824"},{"title":"Node.js 应用：路由","alias":"Node.js App：Routes","url":"https://ninghao.net/course/5806"},{"title":"微信支付：\b小程序支付","alias":"WeChat Pay：wxApp","url":"https://ninghao.net/course/5794"},{"title":"微信支付：公众号支付","alias":"WeChat Pay：JSAPI","url":"https://ninghao.net/course/5780"},{"title":"微信支付：H5 移动端支付","alias":"WeChat Pay：H5","url":"https://ninghao.net/course/5760"},{"title":"微信支付：开发准备与扫码支付","alias":"WeChat Pay：Native","url":"https://ninghao.net/course/5726"},{"title":"Node.js：MVC 框架 - Adonis","alias":"Node.js App：Adonis","url":"https://ninghao.net/course/5710"},{"title":"RxJS：反应式编程","alias":"RxJS：Reactive Programming","url":"https://ninghao.net/course/5694"},{"title":"Redux 与 React","alias":"Redux & React","url":"https://ninghao.net/course/5683"},{"title":"GraphQL：接口查询语言","alias":"GraphQL：API Query Language","url":"https://ninghao.net/course/5661"},{"title":"Vue.js：路由","alias":"Vue.js：Router","url":"https://ninghao.net/course/5086"},{"title":"Redux：数据管理","alias":"Redux：State Management","url":"https://ninghao.net/course/5650"},{"title":"微信小程序：评论功能 #9","alias":"WeChat App & WordPress：Part 9","url":"https://ninghao.net/course/5632"},{"title":"微信小程序：内容评论 #8","alias":"WeChat App & WordPress：Part 8","url":"https://ninghao.net/course/5611"},{"title":"微信小程序：\b微信登录 #7","alias":"WeChat App & WordPress：Part 7","url":"https://ninghao.net/course/5595"},{"title":"Vue.js 前端应用：项目结构","alias":"Vue.js App Structure","url":"https://ninghao.net/course/5580"},{"title":"微信小程序：微信绑定 #6","alias":"WeChat App & WordPress：Part 6","url":"https://ninghao.net/course/5563"},{"title":"微信小程序：用户注册 #5","alias":"WeChat App & WordPress：Part 5","url":"https://ninghao.net/course/5548"},{"title":"微信小程序：文件上传 #4","alias":"WeChat App & WordPress：Part 4","url":"https://ninghao.net/course/5533"},{"title":"微信小程序：身份验证 #3","alias":"WeChat App & WordPress：Part 3","url":"https://ninghao.net/course/5509"},{"title":"微信小程序：内容页面 #2","alias":"WeChat App & WordPress：Part 2","url":"https://ninghao.net/course/5505"},{"title":"Bootstrap 4：表单","alias":"Bootstrap 4：Forms","url":"https://ninghao.net/course/5482"},{"title":"微信小程序：内容列表 #1","alias":"WeChat App & WordPress：Part 1","url":"https://ninghao.net/course/5457"},{"title":"WordPress 开发：开发环境","alias":"WordPress Dev：Local Development Env","url":"https://ninghao.net/course/5245"},{"title":"WordPress 开发：身份验证（JWT）","alias":"WordPress Dev：Aauthentication（JWT）","url":"https://ninghao.net/course/5440"},{"title":"Bootstrap 4：界面组件","alias":"Bootstrap 4：Component","url":"https://ninghao.net/course/5386"},{"title":"Bootstrap 4：网页布局","alias":"Bootstrap 4：Layout","url":"https://ninghao.net/course/5370"},{"title":"Vue.js：应用案例（Vuex）","alias":"Vue.js：Use Case（Vuex）","url":"https://ninghao.net/course/5348"},{"title":"React：应用案例","alias":"React：Use Case","url":"https://ninghao.net/course/5324"},{"title":"Vue.js：应用案例","alias":"Vue.js：Use Case","url":"https://ninghao.net/course/5295"},{"title":"微信小程序：接口","alias":"WeChat App：API","url":"https://ninghao.net/course/5229"},{"title":"WordPress 开发：生产环境","alias":"WordPress Dev：Production Env","url":"https://ninghao.net/course/5270"},{"title":"JavaScript：ES6 新功能","alias":"ECMAScript New Features","url":"https://ninghao.net/course/3032"},{"title":"Python：基础","alias":"Python：Essential","url":"https://ninghao.net/course/5133"},{"title":"微信小程序：案例","alias":"WeChat App：Case","url":"https://ninghao.net/course/5172"},{"title":"在互联网访问本地开发环境","alias":"Access Local Dev Env from Internet","url":"https://ninghao.net/course/5163"},{"title":"Node.js：上传文件","alias":"Node.js：Upload Files","url":"https://ninghao.net/course/5149"},{"title":"Vue.js：数据管理","alias":"Vue.js：Vuex","url":"https://ninghao.net/course/5118"},{"title":"微信小程序：组件","alias":"WeChat App：Components","url":"https://ninghao.net/course/5097"},{"title":"微信小程序：视图","alias":"WeChat App：Views","url":"https://ninghao.net/course/5074"},{"title":"微信小程序：框架","alias":"WeChat App：Framework","url":"https://ninghao.net/course/5054"},{"title":"Node.js：基于 Token 的身份验证","alias":"Node.js：Auth","url":"https://ninghao.net/course/5037"},{"title":"微信小程序：起步","alias":"WeChat App：Getting Started","url":"https://ninghao.net/course/5028"},{"title":"JWT：JSON Web Token","alias":"JWT：JSON Web Token","url":"https://ninghao.net/course/5018"},{"title":"Composer：PHP 项目包管理","alias":"Composer：Dependency Manager for PHP","url":"https://ninghao.net/course/5009"},{"title":"PHP 基础","alias":"PHP Essential","url":"https://ninghao.net/course/1528"},{"title":"PHP：设计模式","alias":"PHP：Design Patterns","url":"https://ninghao.net/course/4997"},{"title":"Node.js：REST 接口","alias":"Node.js：RESTful API","url":"https://ninghao.net/course/4983"},{"title":"Node.js 与 MongoDB","alias":"Node.js and MongoDB","url":"https://ninghao.net/course/4968"},{"title":"Node.js 起步","alias":"Node.js Getting Started","url":"https://ninghao.net/course/4952"},{"title":"Git：版本控制","alias":"Git Version Control","url":"https://ninghao.net/course/1882"},{"title":"Drupal：自定义界面","alias":"Drupal：Custom UI","url":"https://ninghao.net/course/4490"},{"title":"Drupal：媒体","alias":"Drupal：Media","url":"https://ninghao.net/course/4666"},{"title":"Socket.io","alias":"Socket.io","url":"https://ninghao.net/course/4636"},{"title":"Express","alias":"Express","url":"https://ninghao.net/course/4618"},{"title":"准备工具：Windows","alias":"Prepare for Windows","url":"https://ninghao.net/course/4592"},{"title":"准备工具：macOS","alias":"Prepare for macOS","url":"https://ninghao.net/course/4546"},{"title":"HTTPS 与 HTTP2","alias":"HTTPS & HTTP2","url":"https://ninghao.net/course/4539"},{"title":"Drupal 8：电子商务","alias":"Drupal 8：Commerce","url":"https://ninghao.net/course/4460"},{"title":"阿里云：域名","alias":"Aliyun：Domain","url":"https://ninghao.net/course/4518"},{"title":"React Native #1","alias":"React Native App #1","url":"https://ninghao.net/course/3001"},{"title":"React 基础","alias":"React Essential","url":"https://ninghao.net/course/2967"},{"title":"Drupal：Console","alias":"Drupal：Console","url":"https://ninghao.net/course/4478"},{"title":"网站实例：设计","alias":"Case：Design","url":"https://ninghao.net/course/4420"},{"title":"Sketch：插件","alias":"Sketch：Plugins","url":"https://ninghao.net/course/4412"},{"title":"Sketch：技能","alias":"Sketch：Tricks","url":"https://ninghao.net/course/4417"},{"title":"Drupal 8：主题","alias":"Drupal 8：Theme","url":"https://ninghao.net/course/4397"},{"title":"Drupal 8：配置管理","alias":"Drupal 8：Configuration Management","url":"https://ninghao.net/course/4386"},{"title":"Sketch：设计工具","alias":"Sketch：Design Tool","url":"https://ninghao.net/course/4362"},{"title":"准备工作","alias":"Prepare to Work","url":"https://ninghao.net/course/2557"},{"title":"CSS：动画","alias":"CSS：Animation","url":"https://ninghao.net/course/4325"},{"title":"CSS：变换","alias":"CSS：Transforms","url":"https://ninghao.net/course/4313"},{"title":"CSS：过渡","alias":"CSS：Transitions","url":"https://ninghao.net/course/4307"},{"title":"Vue.js：组件","alias":"Vue.js：Components","url":"https://ninghao.net/course/4298"},{"title":"Vue.js 前端框架","alias":"Vue.js Framework","url":"https://ninghao.net/course/4276"},{"title":"Ruby 语言：类","alias":"Ruby Language：Classes","url":"https://ninghao.net/course/4266"},{"title":"Vue.js：预览","alias":"Vue.js：Preview","url":"https://ninghao.net/course/4256"},{"title":"Ruby 语言","alias":"Ruby Language","url":"https://ninghao.net/course/4234"},{"title":"Rails：视图","alias":"Ruby on Rails：Views","url":"https://ninghao.net/course/4218"},{"title":"Rails：控制器","alias":"Ruby on Rails：Controllers","url":"https://ninghao.net/course/4197"},{"title":"Rails：关联","alias":"Ruby on Rails：Associations","url":"https://ninghao.net/course/4154"},{"title":"Rails：查询接口","alias":"Ruby on Rails：Query Interface","url":"https://ninghao.net/course/4171"},{"title":"Rails：数据库 Migration","alias":"Ruby on Rails：Migration","url":"https://ninghao.net/course/4133"},{"title":"Ruby on Rails：起步","alias":"Ruby on Rails：Getting Started","url":"https://ninghao.net/course/4101"},{"title":"Node.js：测试","alias":"Node.js：Testing","url":"https://ninghao.net/course/4065"},{"title":"Ansible：自动化配置","alias":"Ansible：Configuration Automation","url":"https://ninghao.net/course/4032"},{"title":"正则表达式","alias":"Regular Expression","url":"https://ninghao.net/course/4020"},{"title":"NGINX：Web 服务器","alias":"NGINX：Web Server","url":"https://ninghao.net/course/3996"},{"title":"Atom\b：代码编辑器","alias":"Atom Editor","url":"https://ninghao.net/course/2025"},{"title":"Vagrant：虚拟机管理","alias":"Vagrant: Virtual Machine Manager","url":"https://ninghao.net/course/1569"},{"title":"阿里云：专有网络","alias":"Aliyun VPC","url":"https://ninghao.net/course/3968"},{"title":"阿里云：资源编排","alias":"Aliyun ROS","url":"https://ninghao.net/course/3969"},{"title":"WordPress 开发：小工具","alias":"WordPress Development：Widget","url":"https://ninghao.net/course/3959"},{"title":"WordPress 开发：短代码","alias":"WordPress Development：Shortcode","url":"https://ninghao.net/course/3950"},{"title":"WordPress 开发：脚本与样式","alias":"WordPress Development：JS and CSS","url":"https://ninghao.net/course/3939"},{"title":"MongoDB","alias":"MongoDB","url":"https://ninghao.net/course/3898"},{"title":"Node.js 核心模块","alias":"Node.js Core Module","url":"https://ninghao.net/course/3912"},{"title":"WordPress 开发：计划任务","alias":"WordPress Development：Cron","url":"https://ninghao.net/course/3883"},{"title":"Docker：集群","alias":"Docker：Swarm","url":"https://ninghao.net/course/3870"},{"title":"WordPress 开发：设置","alias":"WordPress Development：Settings API","url":"https://ninghao.net/course/3857"},{"title":"Docker 容器化应用","alias":"Docker Compose App","url":"https://ninghao.net/course/3840"},{"title":"Docker：组合","alias":"Docker：Compose","url":"https://ninghao.net/course/3826"},{"title":"Docker：网络","alias":"Docker：Network","url":"https://ninghao.net/course/3814"},{"title":"Docker：存储","alias":"Docker：Data Volumes","url":"https://ninghao.net/course/3808"},{"title":"Swift 语言","alias":"Swift Language","url":"https://ninghao.net/course/3781"},{"title":"Docker：镜像与容器","alias":"Docker：Image and Container","url":"https://ninghao.net/course/3764"},{"title":"Drupal 8：多语言","alias":"Drupal 8：Multilingual","url":"https://ninghao.net/course/3740"},{"title":"Plyr 播放器","alias":"Plyr Player","url":"https://ninghao.net/course/3754"},{"title":"MixItUp：动画过滤与排序","alias":"MixItUp：Animated Filtering and Sorting","url":"https://ninghao.net/course/3730"},{"title":"Drupal 8 开发：区块","alias":"Drupal 8 Development：Block API","url":"https://ninghao.net/course/3719"},{"title":"Drupal 8 开发：表单","alias":"Drupal 8 Development：Form API","url":"https://ninghao.net/course/3708"},{"title":"WordPress 开发：钩子","alias":"WordPress Development：Hooks","url":"https://ninghao.net/course/3698"},{"title":"Drupal 8 开发：资源管理","alias":"Drupal 8 Development：Asset Management","url":"https://ninghao.net/course/3687"},{"title":"Drupal 8 开发：控制器与路由","alias":"Drupal 8 Development","url":"https://ninghao.net/course/3676"},{"title":"WordPress 自定义内容类型","alias":"WordPress Custom Post Type","url":"https://ninghao.net/course/740"},{"title":"WordPress 电子商务网站","alias":"WordPress WooCommerce E-Commerce","url":"https://ninghao.net/course/1775"},{"title":"WordPress 日常维护","alias":"WordPress Daily Maintenance","url":"https://ninghao.net/course/1767"},{"title":"阿里云邮件推送","alias":"Aliyun Direct Mail","url":"https://ninghao.net/course/3631"},{"title":"阿里云 SLB：负载均衡","alias":"Aliyun Server Load Balancer","url":"https://ninghao.net/course/3604"},{"title":"阿里云 RDS：关系数据库","alias":"Aliyun Relational Database Service","url":"https://ninghao.net/course/3594"},{"title":"LEMP 网站应用运行环境","alias":"LEMP Stack","url":"https://ninghao.net/course/2522"},{"title":"阿里云 ECS：Linux 服务器","alias":"Aliyun Elastic Compute Service","url":"https://ninghao.net/course/1584"},{"title":"iptables 防火墙","alias":"iptables Firewall","url":"https://ninghao.net/course/3528"},{"title":"systemctl：Linux 服务管理","alias":"systemctl：System Manager","url":"https://ninghao.net/course/3518"},{"title":"yum：CentOS 包管理工具","alias":"yum：CentOS Package Manager","url":"https://ninghao.net/course/3507"},{"title":"命令行","alias":"Command Line Interface","url":"https://ninghao.net/course/3501"},{"title":"CSS：样式语言","alias":"CSS Language","url":"https://ninghao.net/course/3455"},{"title":"HTML：标记语言","alias":"HTML Markup Language","url":"https://ninghao.net/course/3480"},{"title":"webpack：模块打包","alias":"webpack：Module Bundle","url":"https://ninghao.net/course/3443"},{"title":"Babel：JavaScript 编译工具","alias":"Babel：JavaScript Compiler","url":"https://ninghao.net/course/3432"},{"title":"npm：JavaScript 包管理","alias":"npm：JavaScript Package Manager","url":"https://ninghao.net/course/3421"},{"title":"React Native 组件","alias":"React Native Components","url":"https://ninghao.net/course/3389"},{"title":"Drupal 8 与 React Native","alias":"Drupal 8 & React Native","url":"https://ninghao.net/course/3371"},{"title":"WordPress 与 React Native","alias":"WordPress & React Native","url":"https://ninghao.net/course/3355"},{"title":"Drupal 8：REST 接口","alias":"Drupal 8 REST API","url":"https://ninghao.net/course/3335"},{"title":"WordPress REST 接口","alias":"WordPress REST API","url":"https://ninghao.net/course/3315"},{"title":"Laravel 5：模板","alias":"Laravel 5：Blade","url":"https://ninghao.net/course/3294"},{"title":"Laravel 5：视图","alias":"Laravel 5：Views","url":"https://ninghao.net/course/3281"},{"title":"Laravel 5：控制器","alias":"Laravel 5：Controllers","url":"https://ninghao.net/course/3258"},{"title":"React Native #6：oAuth","alias":"React Native App #6：oAuth","url":"https://ninghao.net/course/3244"},{"title":"Laravel 5：路由","alias":"Laravel 5：Routes","url":"https://ninghao.net/course/3225"},{"title":"Drupal 8：视图（下）","alias":"Drupal 8 Views Part 2","url":"https://ninghao.net/course/3203"},{"title":"oAuth 2.0 身份验证流程","alias":"oAuth 2.0 Workflow","url":"https://ninghao.net/course/3193"},{"title":"Drupal 8：视图（上）","alias":"Drupal 8 Views Part 1","url":"https://ninghao.net/course/3178"},{"title":"React Native #5 滚动分页","alias":"React Native App #5 Infinite Scroll","url":"https://ninghao.net/course/3164"},{"title":"Drupal 8：字段","alias":"Drupal 8 Field","url":"https://ninghao.net/course/3150"},{"title":"React Native #4 存储","alias":"React Native App #4 AsyncStorage","url":"https://ninghao.net/course/3134"},{"title":"React Native #3 文本框","alias":"React Native App #3 TextInput","url":"https://ninghao.net/course/3114"},{"title":"React Native #2 导航","alias":"React Native App #2 Navigate","url":"https://ninghao.net/course/3088"},{"title":"前端工具箱","alias":"Frontend Toolkit","url":"https://ninghao.net/course/3074"},{"title":"React 路由","alias":"React Router","url":"https://ninghao.net/course/2986"},{"title":"CSS：Flexbox 布局","alias":"Flexbox Layout Module","url":"https://ninghao.net/course/2948"},{"title":"前端库","alias":"Frontend Library","url":"https://ninghao.net/course/2939"},{"title":"Bootstrap 4 新功能","alias":"Bootstrap 4 New Features","url":"https://ninghao.net/course/2921"},{"title":"Semantic UI 模块","alias":"Semantic UI Module","url":"https://ninghao.net/course/2836"},{"title":"Semantic UI 集合","alias":"Semantic UI Collections","url":"https://ninghao.net/course/2858"},{"title":"Semantic UI 应用接口","alias":"Semantic UI API","url":"https://ninghao.net/course/2809"},{"title":"Semantic UI 网格","alias":"Semantic UI Grid","url":"https://ninghao.net/course/2796"},{"title":"Semantic UI 视图","alias":"Semantic UI Views","url":"https://ninghao.net/course/2779"},{"title":"Semantic UI 元素","alias":"Semantic UI Elements","url":"https://ninghao.net/course/2753"},{"title":"创建宁皓网 #3：电子商务","alias":"Create Ninghao #3：Commerce","url":"https://ninghao.net/course/2721"},{"title":"游乐场","alias":"Playground","url":"https://ninghao.net/course/2707"},{"title":"Syncthing 文件同步","alias":"Syncthing File Sync","url":"https://ninghao.net/course/2686"},{"title":"Browsersync 浏览器同步","alias":"Synchronised Browser Testing","url":"https://ninghao.net/course/2672"},{"title":"创建宁皓网 #2：内容结构","alias":"Create Ninghao #2：Content Structure","url":"https://ninghao.net/course/2644"},{"title":"创建宁皓网 #1：准备","alias":"Create Ninghao #1：Prepare","url":"https://ninghao.net/course/2620"},{"title":"使用 Ansible","alias":"Using Ansible","url":"https://ninghao.net/course/2580"},{"title":"Linux 文件与目录权限","alias":"Linux File and Directory Permissions","url":"https://ninghao.net/course/2508"},{"title":"Sass 基础","alias":"Sass Essential","url":"https://ninghao.net/course/2094"},{"title":"AngularJS 基础","alias":"AngularJS Essential","url":"https://ninghao.net/course/2034"},{"title":"Gulp 自动化任务","alias":"Gulp: Automate Task","url":"https://ninghao.net/course/2000"},{"title":"Grunt 自动化任务","alias":"Grunt: Automate Task","url":"https://ninghao.net/course/1974"},{"title":"Bower 前端包管理","alias":"Bower: Frontend Package Manager","url":"https://ninghao.net/course/1959"},{"title":"Laravel 身份验证","alias":"Laravel Authentication","url":"https://ninghao.net/course/1921"},{"title":"PHP 面向对象","alias":"PHP: Object Oriented Programming","url":"https://ninghao.net/course/1855"},{"title":"Laravel 数据库","alias":"Laravel: Working with Databases","url":"https://ninghao.net/course/1729"},{"title":"MySQL 基础","alias":"MySQL Essential","url":"https://ninghao.net/course/1736"},{"title":"Drupal 日常维护","alias":"Drupal Daily Maintenance","url":"https://ninghao.net/course/1699"},{"title":"Laravel 4 基础","alias":"Laravel 4 Essential","url":"https://ninghao.net/course/1642"},{"title":"Backbone 应用实例","alias":"Backbone Use Case","url":"https://ninghao.net/course/1510"},{"title":"Bootstrap 3 基础","alias":"Bootstrap 3 Essential","url":"https://ninghao.net/course/1553"},{"title":"Underscore 基础","alias":"Underscore Essential","url":"https://ninghao.net/course/1479"},{"title":"Backbone 基础","alias":"Backbone Essential","url":"https://ninghao.net/course/1444"},{"title":"HTML5：文件系统","alias":"HTML5: FileSystem API","url":"https://ninghao.net/course/1416"},{"title":"HTML5：Web SQL","alias":"HTML5: Web SQL","url":"https://ninghao.net/course/1381"},{"title":"HTML5：文件 API","alias":"HTML5：File API","url":"https://ninghao.net/course/1347"},{"title":"HTML5 与 Bootstrap 应用实例","alias":"HTML5 + Bootstrap Use Case","url":"https://ninghao.net/course/663"},{"title":"HTML5：Web 存储","alias":"HTML5: Web Storage","url":"https://ninghao.net/course/1218"},{"title":"HTML5：应用缓存","alias":"HTML5: Application Cache","url":"https://ninghao.net/course/1279"},{"title":"jQuery 基础","alias":"jQuery Essential","url":"https://ninghao.net/course/1295"},{"title":"JavaScript 基础","alias":"JavaScript Essential","url":"https://ninghao.net/course/1235"},{"title":"Flowplayer 播放器","alias":"Flowplayer","url":"https://ninghao.net/course/1042"},{"title":"Drupal Services 整合外部应用","alias":"Drupal Services","url":"https://ninghao.net/course/1188"},{"title":"PhoneGap 基础","alias":"PhoneGap Essential","url":"https://ninghao.net/course/1143"},{"title":"Emmet：HTML 与 CSS 缩写","alias":"Emmet","url":"https://ninghao.net/course/1123"},{"title":"CSS：选择器","alias":"CSS Selectors","url":"https://ninghao.net/course/1091"},{"title":"JW Player 播放器","alias":"JW Player","url":"https://ninghao.net/course/1068"},{"title":"响应式网页设计","alias":"Responsive Web Design","url":"https://ninghao.net/course/1002"},{"title":"WordPress 插件","alias":"WordPress Plugins","url":"https://ninghao.net/course/864"},{"title":"Drupal 一分钟","alias":"Drupal One Minute","url":"https://ninghao.net/course/982"},{"title":"Wordpress 一分钟","alias":"WordPress One Minute","url":"https://ninghao.net/course/873"},{"title":"Joomla 模板架构：T3","alias":"T3 Framework for Joomla","url":"https://ninghao.net/course/914"},{"title":"Joomla 模板架构：Gantry","alias":"Gantry Framework for Joomla","url":"https://ninghao.net/course/884"},{"title":"Drupal Commerce 电子商务","alias":"Drupal Commerce","url":"https://ninghao.net/course/818"},{"title":"Drupal Rules 自动化操作","alias":"Drupal Rules Automating Actions","url":"https://ninghao.net/course/798"},{"title":"WordPress 内容关系","alias":"WordPress Posts Relation","url":"https://ninghao.net/course/772"},{"title":"WordPress 主题开发","alias":"WordPress Theme Development","url":"https://ninghao.net/course/691"},{"title":"WordPress 基础","alias":"WordPress Essential","url":"https://ninghao.net/course/618"},{"title":"Drupal 7 基础（下）","alias":"Drupal 7 Essential Part 2","url":"https://ninghao.net/course/571"},{"title":"Drupal 7 基础 （上）","alias":"Drupal 7 Essential Part 1","url":"https://ninghao.net/course/546"},{"title":"Joomla 1.5 发布网站","alias":"Launch Joomla Site To The Internet","url":"https://ninghao.net/course/2"},{"title":"Bootstrap 2 基础","alias":"Bootstrap 2 Essential","url":"https://ninghao.net/course/453"},{"title":"使用网格系统布局","alias":"Using 960 Grid System to Create Page Layout","url":"https://ninghao.net/course/271"},{"title":"CSS 基础","alias":"CSS Essential","url":"https://ninghao.net/course/4"},{"title":"CentOS : 在阿里云上运行网站","alias":"CentOS : Running Website On Ali Cloud","url":"https://ninghao.net/course/514"},{"title":"Drupal 7 多语言","alias":"Drupal 7 Multilingual","url":"https://ninghao.net/course/497"},{"title":"Joomla 1.5 基础","alias":"Joomla 1.5 Essential","url":"https://ninghao.net/course/1"},{"title":"Photoshop CS5 网页设计","alias":"Photoshop CS5 for Web Designer","url":"https://ninghao.net/course/3"},{"title":"Drupal 6 基础 （上）","alias":"Drupal 6 Essential Part 1","url":"https://ninghao.net/course/5"},{"title":"搜索引擎优化","alias":"SEO","url":"https://ninghao.net/course/239"},{"title":"Joomla 2.5 模板开发","alias":"Joomla 2.5 Template Development","url":"https://ninghao.net/course/291"},{"title":"Joomla 模板架构：T3","alias":"Using JA T3 Freamwork for Joomla","url":"https://ninghao.net/course/341"},{"title":"Drupal 7 主题开发","alias":"Drupal 7 Theme Development","url":"https://ninghao.net/course/418"},{"title":"Drupal 6 基础（下）","alias":"Drupal 6 Essential Part 2","url":"https://ninghao.net/course/6"},{"title":"Opencart 基础","alias":"Opencart Essential","url":"https://ninghao.net/course/367"},{"title":"Joomla 2.5 权限控制","alias":"Joomla 2.5 Access Control List","url":"https://ninghao.net/course/401"},{"title":"宁皓网","alias":"ninghao.net","url":"https://ninghao.net/course/3404"}]